clearbox_synthetic/__init__.cpython-311-darwin.so
clearbox_synthetic/evaluation/__init__.cpython-311-darwin.so
clearbox_synthetic/evaluation/__init__.py
clearbox_synthetic/evaluation/privacy.cpython-311-darwin.so
clearbox_synthetic/evaluation/privacy/__init__.cpython-311-darwin.so
clearbox_synthetic/evaluation/privacy/__init__.py
clearbox_synthetic/evaluation/privacy/gower_matrix_c.pyx
clearbox_synthetic/evaluation/privacy/privacy.cpython-311-darwin.so
clearbox_synthetic/evaluation/utility/TSTR.cpython-311-darwin.so
clearbox_synthetic/evaluation/utility/__init__.cpython-311-darwin.so
clearbox_synthetic/evaluation/utility/anomalies.cpython-311-darwin.so
clearbox_synthetic/evaluation/utility/autocorrelation.cpython-311-darwin.so
clearbox_synthetic/evaluation/utility/detection.cpython-311-darwin.so
clearbox_synthetic/evaluation/utility/features_comparison.cpython-311-darwin.so
clearbox_synthetic/evaluation/utility/mutual_information.cpython-311-darwin.so
clearbox_synthetic/evaluation/utility/query_power.cpython-311-darwin.so
clearbox_synthetic/evaluation/utility/reconstruction_error.cpython-311-darwin.so
clearbox_synthetic/generation/__init__.cpython-311-darwin.so
clearbox_synthetic/generation/VAE/__init__.cpython-311-darwin.so
clearbox_synthetic/generation/VAE/__init__.py
clearbox_synthetic/generation/VAE/tabular_vae.py
clearbox_synthetic/generation/VAE/timeseries_vae.cpython-311-darwin.so
clearbox_synthetic/generation/VAE/timeseries_vae.py
clearbox_synthetic/generation/VAE/vae.cpython-311-darwin.so
clearbox_synthetic/generation/diffusion/__init__.cpython-311-darwin.so
clearbox_synthetic/generation/diffusion/__init__.py
clearbox_synthetic/generation/diffusion/diffusion.cpython-311-darwin.so
clearbox_synthetic/generation/diffusion/tabular_diffusion.cpython-311-darwin.so
clearbox_synthetic/generation/diffusion/tabular_diffusion.py
clearbox_synthetic/generation/engine/__init__.cpython-311-darwin.so
clearbox_synthetic/generation/engine/__init__.py
clearbox_synthetic_kit-0.6.14.dist-info/LICENSE
clearbox_synthetic_kit-0.6.14.dist-info/METADATA
clearbox_synthetic_kit-0.6.14.dist-info/WHEEL
clearbox_synthetic_kit-0.6.14.dist-info/top_level.txt
clearbox_synthetic_kit-0.6.14.dist-info/RECORD
