Metadata-Version: 2.1
Name: clearbox-synthetic-kit
Version: 0.6.14
Summary: Clearbox AI's all-in-one solution for generation and evaluation of synthetic tabular and time-series data.
Home-page: https://github.com/Clearbox-AI/clearbox-synthetic-kit
Author: Clearbox AI
Author-email: info@clearbox.ai
Requires-Python: >=3.9.0
License-File: LICENSE
Requires-Dist: diffrax
Requires-Dist: equinox
Requires-Dist: jax==0.4.30
Requires-Dist: flax==0.8.5
Requires-Dist: numpy<2.0.0
Requires-Dist: pydantic>=2.0
Requires-Dist: typing
Requires-Dist: pandas<=2.2.3
Requires-Dist: loguru
Requires-Dist: dateparser
Requires-Dist: pyarrow
Requires-Dist: pydateinfer
Requires-Dist: pytest
Requires-Dist: pytest-cov
Requires-Dist: pytest-lazy-fixture
Requires-Dist: scikit-learn
Requires-Dist: scipy<=1.14
Requires-Dist: cython
Requires-Dist: xgboost
Requires-Dist: optax
Requires-Dist: tqdm
Requires-Dist: requests
Requires-Dist: sphinx-rtd-theme
Requires-Dist: myst-parser
Requires-Dist: clearbox-preprocessor
